{"symbol":"خمحرکه","updated":"2026-07-08T06:59:19.569Z","months":[{"period":"1404/01/31","publish":"1404/03/07","products":[],"month":null,"cum":null,"lastYearCum":null},{"period":"1404/02/31","publish":"1404/03/14","products":[{"name":"ست قطعات تراکتور","unit":"ست","prod_m":2390,"qty_m":2287,"rate_m":22609532,"amount_m":51708,"amount_cum":86177},{"name":"قطعات و لوازم","unit":"عدد","prod_m":null,"qty_m":null,"rate_m":null,"amount_m":644734,"amount_cum":649169},{"name":"گیربکس تارا","unit":"دستگاه","prod_m":null,"qty_m":null,"rate_m":null,"amount_m":0,"amount_cum":0},{"name":"گیربکس رانا _BC","unit":"دستگاه","prod_m":11383,"qty_m":13408,"rate_m":137498135,"amount_m":1843575,"amount_cum":3131512},{"name":"گیربکس R۲","unit":"دستگاه","prod_m":null,"qty_m":null,"rate_m":null,"amount_m":0,"amount_cum":0},{"name":"گیربکس پژو پارس","unit":"دستگاه","prod_m":15701,"qty_m":18180,"rate_m":126176128,"amount_m":2293882,"amount_cum":3420759},{"name":"گیربکس ۶ دنده","unit":"دستگاه","prod_m":6399,"qty_m":6388,"rate_m":169779900,"amount_m":1084554,"amount_cum":1780213},{"name":"ست چرخدنده تیبا","unit":"ست","prod_m":5859,"qty_m":6610,"rate_m":37780333,"amount_m":249728,"amount_cum":348297},{"name":"چرخدنده SP۱۰۰","unit":"ست","prod_m":null,"qty_m":null,"rate_m":null,"amount_m":0,"amount_cum":0},{"name":"قطعات و سایر","unit":"دستگاه","prod_m":0,"qty_m":0,"rate_m":null,"amount_m":2468,"amount_cum":2691},{"name":"تخفیفات","unit":null,"prod_m":null,"qty_m":null,"rate_m":null,"amount_m":0,"amount_cum":0}],"month":6170649,"cum":9418818,"lastYearCum":6648284},{"period":"1404/03/31","publish":"1404/04/31","products":[{"name":"ست قطعات تراکتور","unit":"ست","prod_m":1445,"qty_m":1281,"rate_m":20909446,"amount_m":26785,"amount_cum":112962},{"name":"قطعات و لوازم","unit":"عدد","prod_m":null,"qty_m":null,"rate_m":null,"amount_m":2106512,"amount_cum":2755681},{"name":"گیربکس تارا","unit":"دستگاه","prod_m":null,"qty_m":null,"rate_m":null,"amount_m":0,"amount_cum":0},{"name":"گیربکس رانا _BC","unit":"دستگاه","prod_m":13910,"qty_m":12048,"rate_m":137482570,"amount_m":1656390,"amount_cum":4787902},{"name":"گیربکس R۲","unit":"دستگاه","prod_m":null,"qty_m":null,"rate_m":null,"amount_m":0,"amount_cum":0},{"name":"گیربکس پژو پارس","unit":"دستگاه","prod_m":15203,"qty_m":11880,"rate_m":131577609,"amount_m":1563142,"amount_cum":4983901},{"name":"گیربکس ۶ دنده","unit":"دستگاه","prod_m":6781,"qty_m":5424,"rate_m":173247972,"amount_m":939697,"amount_cum":2719910},{"name":"ست چرخدنده تیبا","unit":"ست","prod_m":4998,"qty_m":4379,"rate_m":39352592,"amount_m":172325,"amount_cum":520622},{"name":"چرخدنده SP۱۰۰","unit":"ست","prod_m":null,"qty_m":201,"rate_m":68810945,"amount_m":13831,"amount_cum":13831},{"name":"خدمات آزمایشگاهی","unit":"عدد","prod_m":0,"qty_m":0,"rate_m":0,"amount_m":0,"amount_cum":2691},{"name":"گیربکس ۶ دنده","unit":"دستگاه","prod_m":null,"qty_m":-4,"rate_m":172750000,"amount_m":-691,"amount_cum":-691},{"name":"گیربکس رانا-BC","unit":"دستگاه","prod_m":null,"qty_m":-2,"rate_m":135500000,"amount_m":-271,"amount_cum":-271},{"name":"گیربکس پژو پارس","unit":"دستگاه","prod_m":null,"qty_m":-2,"rate_m":130500000,"amount_m":-261,"amount_cum":-261},{"name":"قطعات و لوازم","unit":"عدد","prod_m":null,"qty_m":null,"rate_m":null,"amount_m":-1254,"amount_cum":-1254},{"name":"ست چرخدنده تیبا","unit":"ست","prod_m":null,"qty_m":-142,"rate_m":39584507,"amount_m":-5621,"amount_cum":-5621},{"name":"تخفیفات","unit":null,"prod_m":null,"qty_m":null,"rate_m":null,"amount_m":0,"amount_cum":0}],"month":6470584,"cum":15889402,"lastYearCum":13895776},{"period":"1404/04/31","publish":"1404/05/07","products":[{"name":"ست قطعات تراکتور","unit":"ست","prod_m":2494,"qty_m":2629,"rate_m":29203499,"amount_m":76776,"amount_cum":189738},{"name":"قطعات و لوازم","unit":"عدد","prod_m":null,"qty_m":null,"rate_m":null,"amount_m":781305,"amount_cum":3536986},{"name":"گیربکس تارا","unit":"دستگاه","prod_m":null,"qty_m":null,"rate_m":null,"amount_m":0,"amount_cum":0},{"name":"گیربکس رانا _BC","unit":"دستگاه","prod_m":8722,"qty_m":9437,"rate_m":140998199,"amount_m":1330600,"amount_cum":6118502},{"name":"گیربکس R۲","unit":"دستگاه","prod_m":null,"qty_m":null,"rate_m":null,"amount_m":0,"amount_cum":0},{"name":"گیربکس پژو پارس","unit":"دستگاه","prod_m":11971,"qty_m":12695,"rate_m":134922883,"amount_m":1712846,"amount_cum":6696747},{"name":"گیربکس ۶ دنده","unit":"دستگاه","prod_m":5347,"qty_m":5734,"rate_m":172344437,"amount_m":988223,"amount_cum":3708133},{"name":"ست چرخدنده تیبا","unit":"ست","prod_m":null,"qty_m":null,"rate_m":null,"amount_m":0,"amount_cum":520622},{"name":"چرخدنده SP۱۰۰","unit":"ست","prod_m":null,"qty_m":null,"rate_m":null,"amount_m":0,"amount_cum":13831},{"name":"خدمات آزمایشگاهی","unit":"عدد","prod_m":0,"qty_m":0,"rate_m":null,"amount_m":3946,"amount_cum":7440},{"name":"گیربکس ۶ دنده","unit":"دستگاه","prod_m":null,"qty_m":-6,"rate_m":174000000,"amount_m":-1044,"amount_cum":-1044},{"name":"گیربکس رانا-BC","unit":"دستگاه","prod_m":null,"qty_m":-57,"rate_m":176596491,"amount_m":-10066,"amount_cum":-10066},{"name":"گیربکس تارا","unit":"دستگاه","prod_m":null,"qty_m":-3,"rate_m":135333333,"amount_m":-406,"amount_cum":-406},{"name":"قطعات و لوازم","unit":"عدد","prod_m":null,"qty_m":null,"rate_m":null,"amount_m":-2282,"amount_cum":-6643},{"name":"تخفیفات","unit":null,"prod_m":null,"qty_m":null,"rate_m":null,"amount_m":0,"amount_cum":0}],"month":4879898,"cum":20772874,"lastYearCum":18604811},{"period":"1404/05/31","publish":"1404/06/12","products":[{"name":"ست قطعات تراکتور","unit":"ست","prod_m":0,"qty_m":1188,"rate_m":24231481,"amount_m":28787,"amount_cum":218525},{"name":"قطعات و لوازم","unit":"عدد","prod_m":0,"qty_m":0,"rate_m":null,"amount_m":1000751,"amount_cum":4537737},{"name":"گیربکس تارا","unit":"دستگاه","prod_m":0,"qty_m":0,"rate_m":null,"amount_m":0,"amount_cum":0},{"name":"گیربکس رانا _BC","unit":"دستگاه","prod_m":12736,"qty_m":13048,"rate_m":138236971,"amount_m":1803716,"amount_cum":7922218},{"name":"گیربکس R۲","unit":"دستگاه","prod_m":0,"qty_m":0,"rate_m":null,"amount_m":0,"amount_cum":0},{"name":"گیربکس پژو پارس","unit":"دستگاه","prod_m":11806,"qty_m":13800,"rate_m":129768986,"amount_m":1790812,"amount_cum":8487559},{"name":"گیربکس ۶ دنده","unit":"دستگاه","prod_m":7810,"qty_m":6000,"rate_m":170023000,"amount_m":1020138,"amount_cum":4728271},{"name":"ست چرخدنده تیبا","unit":"ست","prod_m":0,"qty_m":0,"rate_m":null,"amount_m":0,"amount_cum":520622},{"name":"چرخدنده SP۱۰۰","unit":"ست","prod_m":0,"qty_m":0,"rate_m":null,"amount_m":0,"amount_cum":13831},{"name":"خدمات آزمایشگاهی","unit":"عدد","prod_m":0,"qty_m":0,"rate_m":null,"amount_m":1482,"amount_cum":8922},{"name":"گیربکس رانا-BC","unit":"دستگاه","prod_m":null,"qty_m":-3,"rate_m":155000000,"amount_m":-465,"amount_cum":-10531},{"name":"گیربکس پژو پارس","unit":"دستگاه","prod_m":null,"qty_m":-1,"rate_m":159000000,"amount_m":-159,"amount_cum":-159},{"name":"قطعات و لوازم","unit":"عدد","prod_m":null,"qty_m":0,"rate_m":null,"amount_m":-12595,"amount_cum":-19238},{"name":"ست چرخدنده تیبا","unit":"ست","prod_m":null,"qty_m":-3,"rate_m":14000000,"amount_m":-42,"amount_cum":-122},{"name":"چرخدنده SP۱۰۰","unit":"ست","prod_m":null,"qty_m":-9,"rate_m":64666667,"amount_m":-582,"amount_cum":-1468},{"name":"تخفیفات","unit":null,"prod_m":null,"qty_m":null,"rate_m":null,"amount_m":0,"amount_cum":0}],"month":5631843,"cum":26404717,"lastYearCum":22998553},{"period":"1404/06/31","publish":"1404/08/28","products":[{"name":"ست قطعات تراکتور","unit":"ست","prod_m":3544,"qty_m":3907,"rate_m":29310724,"amount_m":114517,"amount_cum":384855},{"name":"قطعات و لوازم","unit":"عدد","prod_m":0,"qty_m":0,"rate_m":null,"amount_m":1051476,"amount_cum":5598335},{"name":"گیربکس تارا","unit":"دستگاه","prod_m":0,"qty_m":0,"rate_m":null,"amount_m":0,"amount_cum":0},{"name":"گیربکس رانا _BC","unit":"دستگاه","prod_m":16672,"qty_m":16592,"rate_m":176087874,"amount_m":2921650,"amount_cum":11863082},{"name":"گیربکس R۲","unit":"دستگاه","prod_m":null,"qty_m":null,"rate_m":null,"amount_m":0,"amount_cum":0},{"name":"گیربکس پژو پارس","unit":"دستگاه","prod_m":19060,"qty_m":20392,"rate_m":156736956,"amount_m":3196180,"amount_cum":13021154},{"name":"گیربکس ۶ دنده","unit":"دستگاه","prod_m":8422,"qty_m":5944,"rate_m":198203062,"amount_m":1178119,"amount_cum":7410338},{"name":"ست چرخدنده تیبا","unit":"ست","prod_m":0,"qty_m":0,"rate_m":null,"amount_m":0,"amount_cum":501235},{"name":"چرخدنده SP۱۰۰","unit":"ست","prod_m":0,"qty_m":0,"rate_m":null,"amount_m":0,"amount_cum":13832},{"name":"خدمات آزمایشگاهی","unit":"عدد","prod_m":0,"qty_m":0,"rate_m":null,"amount_m":3160,"amount_cum":12046},{"name":"گیربکس ۶ دنده","unit":"دستگاه","prod_m":null,"qty_m":-4,"rate_m":161250000,"amount_m":-645,"amount_cum":-1790},{"name":"گیربکس رانا-BC","unit":"دستگاه","prod_m":null,"qty_m":-2,"rate_m":155000000,"amount_m":-310,"amount_cum":-1998},{"name":"گیربکس پژو پارس","unit":"دستگاه","prod_m":null,"qty_m":0,"rate_m":0,"amount_m":0,"amount_cum":-7502},{"name":"قطعات و لوازم","unit":"عدد","prod_m":null,"qty_m":0,"rate_m":null,"amount_m":-8980,"amount_cum":-47614},{"name":"ست چرخدنده تیبا","unit":"ست","prod_m":null,"qty_m":0,"rate_m":0,"amount_m":null,"amount_cum":-1306},{"name":"چرخدنده SP۱۰۰","unit":"ست","prod_m":null,"qty_m":null,"rate_m":0,"amount_m":0,"amount_cum":-1469},{"name":"گیربکس تارا","unit":"دستگاه","prod_m":null,"qty_m":0,"rate_m":0,"amount_m":0,"amount_cum":0},{"name":"گیربکس R۲","unit":"دستگاه","prod_m":null,"qty_m":0,"rate_m":0,"amount_m":0,"amount_cum":0},{"name":"تخفیفات","unit":null,"prod_m":null,"qty_m":null,"rate_m":null,"amount_m":0,"amount_cum":0}],"month":8455167,"cum":38743198,"lastYearCum":30755235},{"period":"1404/07/30","publish":"1404/08/07","products":[{"name":"ست قطعات تراکتور","unit":"ست","prod_m":95,"qty_m":1202,"rate_m":29309484,"amount_m":35230,"amount_cum":420085},{"name":"قطعات و لوازم","unit":"عدد","prod_m":0,"qty_m":1,"rate_m":1072518000000,"amount_m":1072518,"amount_cum":6627964},{"name":"گیربکس تارا","unit":"دستگاه","prod_m":null,"qty_m":null,"rate_m":null,"amount_m":0,"amount_cum":0},{"name":"گیربکس رانا _BC","unit":"دستگاه","prod_m":17018,"qty_m":15498,"rate_m":176535166,"amount_m":2735942,"amount_cum":14607170},{"name":"گیربکس R۲","unit":"دستگاه","prod_m":0,"qty_m":53,"rate_m":183169811,"amount_m":9708,"amount_cum":9708},{"name":"گیربکس پژو پارس","unit":"دستگاه","prod_m":16389,"qty_m":17149,"rate_m":160229926,"amount_m":2747783,"amount_cum":15768897},{"name":"گیربکس ۶ دنده","unit":"دستگاه","prod_m":7151,"qty_m":9819,"rate_m":216154395,"amount_m":2122420,"amount_cum":9534281},{"name":"ست چرخدنده تیبا","unit":"ست","prod_m":null,"qty_m":null,"rate_m":null,"amount_m":0,"amount_cum":501235},{"name":"چرخدنده SP۱۰۰","unit":"ست","prod_m":null,"qty_m":null,"rate_m":null,"amount_m":0,"amount_cum":13832},{"name":"خدمات آزمایشگاهی","unit":"عدد","prod_m":0,"qty_m":1,"rate_m":19355000000,"amount_m":19355,"amount_cum":31401},{"name":"گیربکس ۶ دنده","unit":"دستگاه","prod_m":null,"qty_m":-68,"rate_m":203632353,"amount_m":-13847,"amount_cum":-15637},{"name":"گیربکس رانا-BC","unit":"دستگاه","prod_m":null,"qty_m":-11,"rate_m":174727273,"amount_m":-1922,"amount_cum":-3920},{"name":"گیربکس پژو پارس","unit":"دستگاه","prod_m":null,"qty_m":-2,"rate_m":154000000,"amount_m":-308,"amount_cum":-7810},{"name":"قطعات و لوازم","unit":"عدد","prod_m":null,"qty_m":-1,"rate_m":11520000000,"amount_m":-11520,"amount_cum":-50272},{"name":"ست چرخدنده تیبا","unit":"ست","prod_m":null,"qty_m":1,"rate_m":-9000000,"amount_m":-9,"amount_cum":-132},{"name":"چرخدنده SP۱۰۰","unit":"ست","prod_m":null,"qty_m":-9,"rate_m":64444444,"amount_m":-580,"amount_cum":-2049},{"name":"تخفیفات","unit":null,"prod_m":null,"qty_m":null,"rate_m":null,"amount_m":0,"amount_cum":0}],"month":8714770,"cum":47434753,"lastYearCum":36765801},{"period":"1404/08/30","publish":"1404/09/05","products":[{"name":"ست قطعات تراکتور","unit":"ست","prod_m":1380,"qty_m":1334,"rate_m":29321589,"amount_m":39115,"amount_cum":459200},{"name":"قطعات و لوازم","unit":"عدد","prod_m":0,"qty_m":1,"rate_m":1642334000000,"amount_m":1642334,"amount_cum":8313187},{"name":"گیربکس تارا","unit":"دستگاه","prod_m":null,"qty_m":null,"rate_m":null,"amount_m":0,"amount_cum":0},{"name":"گیربکس رانا _BC","unit":"دستگاه","prod_m":15464,"qty_m":15382,"rate_m":176584384,"amount_m":2716221,"amount_cum":17315245},{"name":"گیربکس R۲","unit":"دستگاه","prod_m":null,"qty_m":null,"rate_m":null,"amount_m":0,"amount_cum":0},{"name":"گیربکس پژو پارس","unit":"دستگاه","prod_m":15631,"qty_m":17608,"rate_m":157476431,"amount_m":2772845,"amount_cum":18551490},{"name":"گیربکس ۶ دنده","unit":"دستگاه","prod_m":12909,"qty_m":12240,"rate_m":218434967,"amount_m":2673644,"amount_cum":12206402},{"name":"ست چرخدنده تیبا","unit":"ست","prod_m":null,"qty_m":null,"rate_m":null,"amount_m":0,"amount_cum":501235},{"name":"چرخدنده SP۱۰۰","unit":"ست","prod_m":null,"qty_m":null,"rate_m":null,"amount_m":0,"amount_cum":13832},{"name":"خدمات آزمایشگاهی","unit":"عدد","prod_m":0,"qty_m":1,"rate_m":5619000000,"amount_m":5619,"amount_cum":37020},{"name":"گیربکس ۶ دنده","unit":"دستگاه","prod_m":null,"qty_m":-5,"rate_m":219800000,"amount_m":-1099,"amount_cum":-16736},{"name":"گیربکس رانا-BC","unit":"دستگاه","prod_m":null,"qty_m":-1,"rate_m":175000000,"amount_m":-175,"amount_cum":-4095},{"name":"قطعات و لوازم","unit":"عدد","prod_m":null,"qty_m":-1,"rate_m":8000000,"amount_m":-8,"amount_cum":-59142},{"name":"تخفیفات","unit":null,"prod_m":null,"qty_m":null,"rate_m":null,"amount_m":0,"amount_cum":0}],"month":9848496,"cum":57306464,"lastYearCum":42518228},{"period":"1404/09/30","publish":"1404/10/07","products":[{"name":"ست قطعات تراکتور","unit":"ست","prod_m":1695,"qty_m":1586,"rate_m":43446406,"amount_m":68906,"amount_cum":528106},{"name":"قطعات و لوازم","unit":"عدد","prod_m":null,"qty_m":1,"rate_m":4016995000000,"amount_m":4016995,"amount_cum":12330182},{"name":"گیربکس تارا","unit":"دستگاه","prod_m":null,"qty_m":null,"rate_m":null,"amount_m":0,"amount_cum":0},{"name":"گیربکس رانا _BC","unit":"دستگاه","prod_m":14269,"qty_m":15542,"rate_m":176691481,"amount_m":2746139,"amount_cum":20051294},{"name":"گیربکس R۲","unit":"دستگاه","prod_m":null,"qty_m":null,"rate_m":null,"amount_m":0,"amount_cum":8061},{"name":"گیربکس پژو پارس","unit":"دستگاه","prod_m":18818,"qty_m":17338,"rate_m":175487888,"amount_m":3042609,"amount_cum":21575843},{"name":"گیربکس ۶ دنده","unit":"دستگاه","prod_m":12271,"qty_m":9352,"rate_m":215646065,"amount_m":2016722,"amount_cum":14221611},{"name":"ست چرخدنده تیبا","unit":"ست","prod_m":null,"qty_m":null,"rate_m":null,"amount_m":0,"amount_cum":501235},{"name":"چرخدنده SP۱۰۰","unit":"ست","prod_m":null,"qty_m":null,"rate_m":null,"amount_m":0,"amount_cum":13832},{"name":"خدمات آزمایشگاهی","unit":"عدد","prod_m":0,"qty_m":1,"rate_m":7551000000,"amount_m":7551,"amount_cum":39384},{"name":"گیربکس ۶ دنده","unit":"دستگاه","prod_m":null,"qty_m":-3,"rate_m":219666667,"amount_m":-659,"amount_cum":-18047},{"name":"گیربکس رانا-BC","unit":"دستگاه","prod_m":null,"qty_m":-3,"rate_m":176666667,"amount_m":-530,"amount_cum":-4737},{"name":"قطعات و لوازم","unit":"عدد","prod_m":null,"qty_m":-1,"rate_m":3013000000,"amount_m":-3013,"amount_cum":-56479},{"name":"تخفیفات","unit":null,"prod_m":null,"qty_m":null,"rate_m":null,"amount_m":0,"amount_cum":0}],"month":11894720,"cum":69177175,"lastYearCum":47614771},{"period":"1404/10/30","publish":"1404/11/07","products":[{"name":"ست قطعات تراکتور","unit":"ست","prod_m":1357,"qty_m":1402,"rate_m":48373039,"amount_m":67819,"amount_cum":595925},{"name":"قطعات و لوازم","unit":"عدد","prod_m":0,"qty_m":1,"rate_m":1399491000000,"amount_m":1399491,"amount_cum":13664586},{"name":"گیربکس تارا","unit":"دستگاه","prod_m":0,"qty_m":0,"rate_m":null,"amount_m":0,"amount_cum":0},{"name":"گیربکس رانا _BC","unit":"دستگاه","prod_m":13992,"qty_m":12736,"rate_m":176750079,"amount_m":2251089,"amount_cum":22323270},{"name":"گیربکس R۲","unit":"دستگاه","prod_m":2,"qty_m":72,"rate_m":186819444,"amount_m":13451,"amount_cum":21512},{"name":"گیربکس پژو پارس","unit":"دستگاه","prod_m":16192,"qty_m":15400,"rate_m":187080909,"amount_m":2881046,"amount_cum":24492545},{"name":"گیربکس ۶ دنده","unit":"دستگاه","prod_m":9892,"qty_m":9096,"rate_m":215190193,"amount_m":1957370,"amount_cum":16124831},{"name":"ست چرخدنده تیبا","unit":"ست","prod_m":0,"qty_m":0,"rate_m":null,"amount_m":0,"amount_cum":501235},{"name":"چرخدنده SP۱۰۰","unit":"ست","prod_m":0,"qty_m":0,"rate_m":null,"amount_m":0,"amount_cum":13832},{"name":"خدمات آزمایشگاهی","unit":"عدد","prod_m":0,"qty_m":1,"rate_m":3257000000,"amount_m":3257,"amount_cum":42641},{"name":"گیربکس ۶ دنده","unit":"دستگاه","prod_m":null,"qty_m":1,"rate_m":-226000000,"amount_m":-226,"amount_cum":-18197},{"name":"گیربکس رانا-BC","unit":"دستگاه","prod_m":null,"qty_m":1,"rate_m":-177000000,"amount_m":-177,"amount_cum":-4919},{"name":"قطعات و لوازم","unit":"عدد","prod_m":null,"qty_m":1,"rate_m":-22997000000,"amount_m":-22997,"amount_cum":-79746},{"name":"تخفیفات","unit":null,"prod_m":null,"qty_m":null,"rate_m":null,"amount_m":0,"amount_cum":0}],"month":8550123,"cum":77664405,"lastYearCum":54311094},{"period":"1404/11/30","publish":"1404/12/06","products":[{"name":"ست قطعات تراکتور","unit":"ست","prod_m":2204,"qty_m":2254,"rate_m":46100710,"amount_m":103911,"amount_cum":699836},{"name":"قطعات و لوازم","unit":"عدد","prod_m":0,"qty_m":1,"rate_m":1400940000000,"amount_m":1400940,"amount_cum":15064642},{"name":"گیربکس تارا","unit":"دستگاه","prod_m":0,"qty_m":0,"rate_m":null,"amount_m":0,"amount_cum":0},{"name":"گیربکس رانا _BC","unit":"دستگاه","prod_m":13354,"qty_m":14416,"rate_m":177148307,"amount_m":2553770,"amount_cum":24877040},{"name":"گیربکس R۲","unit":"دستگاه","prod_m":100,"qty_m":24,"rate_m":182666667,"amount_m":4384,"amount_cum":25896},{"name":"گیربکس پژو پارس","unit":"دستگاه","prod_m":16501,"qty_m":16344,"rate_m":187319322,"amount_m":3061547,"amount_cum":27554092},{"name":"گیربکس ۶ دنده","unit":"دستگاه","prod_m":8540,"qty_m":10544,"rate_m":217374431,"amount_m":2291996,"amount_cum":18461649},{"name":"ست چرخدنده تیبا","unit":"ست","prod_m":null,"qty_m":null,"rate_m":null,"amount_m":0,"amount_cum":501235},{"name":"چرخدنده SP۱۰۰","unit":"ست","prod_m":null,"qty_m":null,"rate_m":null,"amount_m":0,"amount_cum":13832},{"name":"خدمات آزمایشگاهی","unit":"عدد","prod_m":0,"qty_m":1,"rate_m":1810000000,"amount_m":1810,"amount_cum":45308},{"name":"گیربکس ۶ دنده","unit":"دستگاه","prod_m":null,"qty_m":-1,"rate_m":226000000,"amount_m":-226,"amount_cum":-18500},{"name":"گیربکس رانا-BC","unit":"دستگاه","prod_m":null,"qty_m":-3,"rate_m":176666667,"amount_m":-530,"amount_cum":-5449},{"name":"قطعات و لوازم","unit":"عدد","prod_m":null,"qty_m":-1,"rate_m":15404000000,"amount_m":-15404,"amount_cum":-95150},{"name":"تخفیفات","unit":null,"prod_m":null,"qty_m":null,"rate_m":null,"amount_m":0,"amount_cum":0}],"month":9402198,"cum":87101530,"lastYearCum":62540812},{"period":"1404/12/29","publish":"1405/04/10","products":[{"name":"ست قطعات تراکتور","unit":"ست","prod_m":0,"qty_m":0,"rate_m":null,"amount_m":0,"amount_cum":699836},{"name":"قطعات و لوازم","unit":"عدد","prod_m":0,"qty_m":1,"rate_m":4681197000000,"amount_m":4681197,"amount_cum":19490240},{"name":"گیربکس تارا","unit":"دستگاه","prod_m":null,"qty_m":null,"rate_m":null,"amount_m":0,"amount_cum":0},{"name":"گیربکس رانا _BC","unit":"دستگاه","prod_m":8075,"qty_m":4704,"rate_m":219670918,"amount_m":1033332,"amount_cum":27934646},{"name":"گیربکس R۲","unit":"دستگاه","prod_m":300,"qty_m":312,"rate_m":227259615,"amount_m":70905,"amount_cum":100993},{"name":"گیربکس پژو پارس","unit":"دستگاه","prod_m":9084,"qty_m":5936,"rate_m":230248989,"amount_m":1366758,"amount_cum":31277665},{"name":"گیربکس ۶ دنده","unit":"دستگاه","prod_m":4873,"qty_m":3200,"rate_m":294680000,"amount_m":942976,"amount_cum":21758688},{"name":"ست چرخدنده تیبا","unit":"ست","prod_m":null,"qty_m":null,"rate_m":null,"amount_m":0,"amount_cum":676309},{"name":"چرخدنده SP۱۰۰","unit":"ست","prod_m":null,"qty_m":null,"rate_m":null,"amount_m":0,"amount_cum":17748},{"name":"خدمات آزمایشگاهی","unit":"عدد","prod_m":0,"qty_m":1,"rate_m":3957000000,"amount_m":3957,"amount_cum":49265},{"name":"سود سهام","unit":"ریال","prod_m":0,"qty_m":1,"rate_m":500000000000,"amount_m":500000,"amount_cum":500000},{"name":"گیربکس ۶ دنده","unit":"دستگاه","prod_m":null,"qty_m":-121,"rate_m":302528926,"amount_m":-36606,"amount_cum":-56877},{"name":"گیربکس رانا-BC","unit":"دستگاه","prod_m":null,"qty_m":-122,"rate_m":218500000,"amount_m":-26657,"amount_cum":-32473},{"name":"قطعات و لوازم","unit":"عدد","prod_m":null,"qty_m":1,"rate_m":-5945000000,"amount_m":-5945,"amount_cum":-101448},{"name":"تخفیفات","unit":null,"prod_m":null,"qty_m":null,"rate_m":null,"amount_m":0,"amount_cum":0}],"month":8529917,"cum":102287802,"lastYearCum":70983751},{"period":"1405/01/31","publish":"1405/02/03","products":[],"month":null,"cum":null,"lastYearCum":null},{"period":"1405/02/31","publish":"1405/04/08","products":[{"name":"ست قطعات تراکتور","unit":"ست","prod_m":1311,"qty_m":1312,"rate_m":43208841,"amount_m":56690,"amount_cum":100787},{"name":"قطعات و لوازم","unit":"عدد","prod_m":null,"qty_m":1,"rate_m":588072000000,"amount_m":588072,"amount_cum":3378549},{"name":"گیربکس تارا","unit":"دستگاه","prod_m":null,"qty_m":null,"rate_m":null,"amount_m":0,"amount_cum":0},{"name":"گیربکس رانا _BC","unit":"دستگاه","prod_m":12761,"qty_m":15048,"rate_m":243233785,"amount_m":3660182,"amount_cum":4598875},{"name":"گیربکس R۲","unit":"دستگاه","prod_m":242,"qty_m":95,"rate_m":226536842,"amount_m":21521,"amount_cum":30583},{"name":"گیربکس پژو پارس","unit":"دستگاه","prod_m":10718,"qty_m":10656,"rate_m":236053491,"amount_m":2515386,"amount_cum":3476120},{"name":"گیربکس ۶ دنده","unit":"دستگاه","prod_m":5567,"qty_m":7608,"rate_m":289875657,"amount_m":2205374,"amount_cum":2858539},{"name":"ست چرخدنده تیبا","unit":"ست","prod_m":null,"qty_m":null,"rate_m":null,"amount_m":0,"amount_cum":0},{"name":"چرخدنده SP۱۰۰","unit":"ست","prod_m":null,"qty_m":null,"rate_m":null,"amount_m":0,"amount_cum":0},{"name":"خدمات آزمایشگاهی","unit":"عدد","prod_m":0,"qty_m":1,"rate_m":2768000000,"amount_m":2768,"amount_cum":3368},{"name":"گیربکس ۶ دنده","unit":"دستگاه","prod_m":null,"qty_m":-1,"rate_m":282000000,"amount_m":-282,"amount_cum":-282},{"name":"گیربکس رانا-BC","unit":"دستگاه","prod_m":null,"qty_m":-1,"rate_m":219000000,"amount_m":-219,"amount_cum":-219},{"name":"گیربکس پژو پارس","unit":"دستگاه","prod_m":null,"qty_m":-1,"rate_m":227000000,"amount_m":-227,"amount_cum":-227},{"name":"قطعات و لوازم","unit":"عدد","prod_m":null,"qty_m":-1,"rate_m":54000000,"amount_m":-54,"amount_cum":-3096},{"name":"تخفیفات","unit":null,"prod_m":null,"qty_m":null,"rate_m":null,"amount_m":0,"amount_cum":0}],"month":9049211,"cum":14442997,"lastYearCum":9418818},{"period":"1405/03/31","publish":"1405/04/08","products":[{"name":"ست قطعات تراکتور","unit":"ست","prod_m":806,"qty_m":805,"rate_m":57522981,"amount_m":46306,"amount_cum":147093},{"name":"قطعات و لوازم","unit":"عدد","prod_m":null,"qty_m":1,"rate_m":643867000000,"amount_m":643867,"amount_cum":4022416},{"name":"گیربکس تارا","unit":"دستگاه","prod_m":null,"qty_m":null,"rate_m":null,"amount_m":0,"amount_cum":0},{"name":"گیربکس رانا _BC","unit":"دستگاه","prod_m":14874,"qty_m":15344,"rate_m":225964416,"amount_m":3467198,"amount_cum":8066073},{"name":"گیربکس R۲","unit":"دستگاه","prod_m":510,"qty_m":520,"rate_m":236361538,"amount_m":122908,"amount_cum":153491},{"name":"گیربکس پژو پارس","unit":"دستگاه","prod_m":10600,"qty_m":14096,"rate_m":279739713,"amount_m":3943211,"amount_cum":7419331},{"name":"گیربکس ۶ دنده","unit":"دستگاه","prod_m":10903,"qty_m":11119,"rate_m":293815631,"amount_m":3266936,"amount_cum":6125475},{"name":"ست چرخدنده تیبا","unit":"ست","prod_m":null,"qty_m":null,"rate_m":null,"amount_m":0,"amount_cum":0},{"name":"چرخدنده SP۱۰۰","unit":"ست","prod_m":null,"qty_m":null,"rate_m":null,"amount_m":0,"amount_cum":0},{"name":"خدمات آزمایشگاهی","unit":"عدد","prod_m":0,"qty_m":1,"rate_m":1704000000,"amount_m":1704,"amount_cum":5072},{"name":"گیربکس ۶ دنده","unit":"دستگاه","prod_m":null,"qty_m":-13,"rate_m":293307692,"amount_m":-3813,"amount_cum":-4095},{"name":"گیربکس رانا-BC","unit":"دستگاه","prod_m":null,"qty_m":-2,"rate_m":218500000,"amount_m":-437,"amount_cum":-656},{"name":"قطعات و لوازم","unit":"عدد","prod_m":null,"qty_m":-1,"rate_m":936000000,"amount_m":-936,"amount_cum":-4032},{"name":"تخفیفات","unit":null,"prod_m":null,"qty_m":null,"rate_m":null,"amount_m":0,"amount_cum":0}],"month":11486944,"cum":25929941,"lastYearCum":15892976}],"quarters":[{"period":"1404/03/31","months":3,"audited":false,"consolidated":false,"publish":"1404/05/26","revenue":15889402,"revenue_ly":13895776,"gross":371831,"gross_ly":816846,"net":-526608,"net_ly":-342541,"eps":-92,"eps_ly":-60,"capital":5734089,"capital_ly":5734089},{"period":"1404/06/31","months":6,"audited":false,"consolidated":false,"publish":"1404/08/06","revenue":38719983,"revenue_ly":30755235,"gross":408745,"gross_ly":2034797,"net":-1780172,"net_ly":-432371,"eps":-310,"eps_ly":-75,"capital":5734089,"capital_ly":5734089},{"period":"1404/09/30","months":9,"audited":false,"consolidated":false,"publish":"1404/11/07","revenue":69177175,"revenue_ly":47614771,"gross":-200170,"gross_ly":2070437,"net":-3835386,"net_ly":-1122956,"eps":-669,"eps_ly":-196,"capital":5734089,"capital_ly":5734089}]}