{"symbol":"دامین","updated":"2026-07-07T17:16:35.305Z","months":[{"period":"1403/12/30","publish":"1404/03/18","products":[{"name":"قرص روکش دار(دراژه)","unit":"عدد","prod_m":35624740,"qty_m":15037275,"rate_m":8849,"amount_m":133069,"amount_cum":5533895},{"name":"کلیه محصولات خریداری شده","unit":"عدد","prod_m":null,"qty_m":4221,"rate_m":332623,"amount_m":1404,"amount_cum":90388},{"name":"سایر","unit":"عدد","prod_m":null,"qty_m":null,"rate_m":null,"amount_m":0,"amount_cum":0},{"name":"شربت","unit":"شیشه","prod_m":1118604,"qty_m":55480,"rate_m":180678,"amount_m":10024,"amount_cum":2382530},{"name":"قرص","unit":"عدد","prod_m":42442520,"qty_m":19807300,"rate_m":6888,"amount_m":136431,"amount_cum":3119399},{"name":"قطره","unit":"شیشه","prod_m":245823,"qty_m":70274,"rate_m":153698,"amount_m":10801,"amount_cum":572747},{"name":"کپسول","unit":"عدد","prod_m":17523330,"qty_m":9025791,"rate_m":13730,"amount_m":123927,"amount_cum":3034363},{"name":"قرص{کارمزدی}","unit":"عدد","prod_m":14747140,"qty_m":19598800,"rate_m":2531,"amount_m":49613,"amount_cum":361997},{"name":"سایر","unit":"عدد","prod_m":65631,"qty_m":10080,"rate_m":954960,"amount_m":9626,"amount_cum":17874},{"name":"شربت {کارمزدی}","unit":"شیشه","prod_m":60565,"qty_m":74782,"rate_m":339975,"amount_m":25424,"amount_cum":215862},{"name":"کپسول{کارمزدی}","unit":"عدد","prod_m":2892480,"qty_m":2892480,"rate_m":1757,"amount_m":5081,"amount_cum":75044},{"name":"قطره {کارمزدی}","unit":"شیشه","prod_m":null,"qty_m":null,"rate_m":0,"amount_m":0,"amount_cum":145240},{"name":"قرص روکش دار(دراژه)-{کارمزدی}","unit":"عدد","prod_m":34080190,"qty_m":26178840,"rate_m":2002,"amount_m":52398,"amount_cum":947726},{"name":"کلیه محصولات","unit":"عدد","prod_m":null,"qty_m":-121670,"rate_m":12074,"amount_m":-1469,"amount_cum":-84640},{"name":"تخفیفات","unit":null,"prod_m":null,"qty_m":null,"rate_m":null,"amount_m":-163866,"amount_cum":-3196383}],"month":392463,"cum":13216042,"lastYearCum":12105093},{"period":"1404/01/31","publish":"1404/02/06","products":[],"month":null,"cum":null,"lastYearCum":null},{"period":"1404/03/31","publish":"1404/04/04","products":[{"name":"کلیه محصولات خریداری شده","unit":"عدد","prod_m":null,"qty_m":null,"rate_m":null,"amount_m":0,"amount_cum":6974},{"name":"کپسول","unit":"عدد","prod_m":3861700,"qty_m":16202315,"rate_m":13722,"amount_m":222321,"amount_cum":384758},{"name":"قرص روکش دار(دراژه)","unit":"عدد","prod_m":3030010,"qty_m":31050559,"rate_m":10430,"amount_m":323862,"amount_cum":711091},{"name":"قرص","unit":"عدد","prod_m":10947300,"qty_m":43311276,"rate_m":6557,"amount_m":283978,"amount_cum":587609},{"name":"قطره","unit":"شیشه","prod_m":null,"qty_m":203128,"rate_m":163040,"amount_m":33118,"amount_cum":55335},{"name":"شربت","unit":"شیشه","prod_m":252430,"qty_m":824367,"rate_m":203350,"amount_m":167635,"amount_cum":279485},{"name":"سایر","unit":"عدد","prod_m":null,"qty_m":1905,"rate_m":1224672,"amount_m":2333,"amount_cum":2333},{"name":"قطره {کارمزدی}","unit":"شیشه","prod_m":329842,"qty_m":221802,"rate_m":135882,"amount_m":30139,"amount_cum":75419},{"name":"قرص{کارمزدی}","unit":"عدد","prod_m":9513240,"qty_m":5945850,"rate_m":4521,"amount_m":26882,"amount_cum":66351},{"name":"قرص روکش دار(دراژه)-{کارمزدی}","unit":"عدد","prod_m":5568630,"qty_m":1590800,"rate_m":5937,"amount_m":9444,"amount_cum":173609},{"name":"شربت {کارمزدی}","unit":"شیشه","prod_m":99143,"qty_m":16170,"rate_m":180025,"amount_m":2911,"amount_cum":18325},{"name":"کپسول{کارمزدی}","unit":"عدد","prod_m":0,"qty_m":0,"rate_m":0,"amount_m":0,"amount_cum":0},{"name":"سایر","unit":"عدد","prod_m":0,"qty_m":0,"rate_m":0,"amount_m":0,"amount_cum":0},{"name":"تخفیفات","unit":null,"prod_m":null,"qty_m":null,"rate_m":null,"amount_m":-245582,"amount_cum":-612062}],"month":857041,"cum":1749227,"lastYearCum":3176178},{"period":"1404/05/31","publish":"1404/06/05","products":[{"name":"کلیه محصولات خریداری شده","unit":"عدد","prod_m":null,"qty_m":14022,"rate_m":99201,"amount_m":1391,"amount_cum":10969},{"name":"کپسول","unit":"عدد","prod_m":22719600,"qty_m":5639553,"rate_m":27512,"amount_m":155155,"amount_cum":655806},{"name":"قرص روکش دار(دراژه)","unit":"عدد","prod_m":42464510,"qty_m":44675665,"rate_m":8835,"amount_m":394726,"amount_cum":1544631},{"name":"قرص","unit":"عدد","prod_m":108752541,"qty_m":21791689,"rate_m":10188,"amount_m":222011,"amount_cum":1072814},{"name":"قطره","unit":"شیشه","prod_m":175686,"qty_m":27425,"rate_m":168058,"amount_m":4609,"amount_cum":73285},{"name":"شربت","unit":"شیشه","prod_m":1008954,"qty_m":840452,"rate_m":200002,"amount_m":168092,"amount_cum":654001},{"name":"سایر","unit":"عدد","prod_m":null,"qty_m":null,"rate_m":null,"amount_m":0,"amount_cum":2333},{"name":"قطره {کارمزدی}","unit":"شیشه","prod_m":237056,"qty_m":347420,"rate_m":139557,"amount_m":48485,"amount_cum":185856},{"name":"قرص{کارمزدی}","unit":"عدد","prod_m":16207990,"qty_m":13795920,"rate_m":2144,"amount_m":29573,"amount_cum":180046},{"name":"قرص روکش دار(دراژه)-{کارمزدی}","unit":"عدد","prod_m":22420700,"qty_m":41256030,"rate_m":3680,"amount_m":151826,"amount_cum":432576},{"name":"شربت {کارمزدی}","unit":"شیشه","prod_m":187701,"qty_m":92093,"rate_m":291108,"amount_m":26809,"amount_cum":51169},{"name":"کپسول{کارمزدی}","unit":"عدد","prod_m":479022,"qty_m":0,"rate_m":0,"amount_m":0,"amount_cum":0},{"name":"سایر","unit":"عدد","prod_m":0,"qty_m":0,"rate_m":0,"amount_m":0,"amount_cum":0},{"name":"تخفیفات","unit":null,"prod_m":null,"qty_m":null,"rate_m":null,"amount_m":-194421,"amount_cum":-1236838}],"month":1008256,"cum":3538355,"lastYearCum":5924104},{"period":"1404/06/31","publish":"1404/09/08","products":[{"name":"کلیه محصولات خریداری شده","unit":"عدد","prod_m":0,"qty_m":9777,"rate_m":190038,"amount_m":1858,"amount_cum":12827},{"name":"کپسول","unit":"عدد","prod_m":25906100,"qty_m":12887734,"rate_m":18180,"amount_m":234301,"amount_cum":890107},{"name":"قرص روکش دار(دراژه)","unit":"عدد","prod_m":44033940,"qty_m":39857596,"rate_m":7312,"amount_m":291458,"amount_cum":1836089},{"name":"قرص","unit":"عدد","prod_m":68797590,"qty_m":56878765,"rate_m":4617,"amount_m":262623,"amount_cum":1335437},{"name":"قطره","unit":"شیشه","prod_m":0,"qty_m":83253,"rate_m":267714,"amount_m":22288,"amount_cum":95573},{"name":"شربت","unit":"شیشه","prod_m":588956,"qty_m":742998,"rate_m":249586,"amount_m":185442,"amount_cum":839443},{"name":"سایر","unit":"عدد","prod_m":0,"qty_m":null,"rate_m":null,"amount_m":0,"amount_cum":2333},{"name":"قطره {کارمزدی}","unit":"شیشه","prod_m":221854,"qty_m":221854,"rate_m":160002,"amount_m":35497,"amount_cum":221353},{"name":"قرص{کارمزدی}","unit":"عدد","prod_m":9925950,"qty_m":17619880,"rate_m":5102,"amount_m":89904,"amount_cum":269950},{"name":"قرص روکش دار(دراژه)-{کارمزدی}","unit":"عدد","prod_m":11055300,"qty_m":13775040,"rate_m":8147,"amount_m":112229,"amount_cum":544805},{"name":"شربت {کارمزدی}","unit":"شیشه","prod_m":465575,"qty_m":627054,"rate_m":187925,"amount_m":117839,"amount_cum":169008},{"name":"کپسول{کارمزدی}","unit":"عدد","prod_m":0,"qty_m":1179106,"rate_m":1760,"amount_m":2075,"amount_cum":2075},{"name":"سایر","unit":"عدد","prod_m":0,"qty_m":0,"rate_m":0,"amount_m":0,"amount_cum":0},{"name":"تخفیفات","unit":null,"prod_m":null,"qty_m":null,"rate_m":null,"amount_m":-301172,"amount_cum":-1227493}],"month":1054342,"cum":4571979,"lastYearCum":6911162},{"period":"1404/08/30","publish":"1404/10/06","products":[{"name":"کلیه محصولات خریداری شده","unit":"عدد","prod_m":0,"qty_m":939,"rate_m":1464324,"amount_m":1375,"amount_cum":16624},{"name":"کپسول","unit":"عدد","prod_m":17958900,"qty_m":22876126,"rate_m":14305,"amount_m":327246,"amount_cum":1667473},{"name":"قرص روکش دار(دراژه)","unit":"عدد","prod_m":47041360,"qty_m":76392334,"rate_m":8047,"amount_m":614691,"amount_cum":3070659},{"name":"قرص","unit":"عدد","prod_m":40526200,"qty_m":60247487,"rate_m":6999,"amount_m":421652,"amount_cum":2465304},{"name":"قطره","unit":"شیشه","prod_m":0,"qty_m":15176,"rate_m":263047,"amount_m":3992,"amount_cum":129214},{"name":"شربت","unit":"شیشه","prod_m":68453,"qty_m":640314,"rate_m":260550,"amount_m":166834,"amount_cum":1374524},{"name":"سایر","unit":"عدد","prod_m":0,"qty_m":0,"rate_m":null,"amount_m":0,"amount_cum":2333},{"name":"قطره {کارمزدی}","unit":"شیشه","prod_m":357168,"qty_m":303062,"rate_m":139671,"amount_m":42329,"amount_cum":281390},{"name":"قرص{کارمزدی}","unit":"عدد","prod_m":10418080,"qty_m":2456520,"rate_m":5911,"amount_m":14520,"amount_cum":284470},{"name":"قرص روکش دار(دراژه)-{کارمزدی}","unit":"عدد","prod_m":21872700,"qty_m":21846330,"rate_m":3491,"amount_m":76275,"amount_cum":702755},{"name":"شربت {کارمزدی}","unit":"شیشه","prod_m":924286,"qty_m":971183,"rate_m":144373,"amount_m":140213,"amount_cum":383272},{"name":"کپسول{کارمزدی}","unit":"عدد","prod_m":3050160,"qty_m":3494848,"rate_m":5013,"amount_m":17518,"amount_cum":21248},{"name":"سایر","unit":"عدد","prod_m":0,"qty_m":0,"rate_m":0,"amount_m":0,"amount_cum":0},{"name":"کلیه محصولات","unit":"عدد","prod_m":null,"qty_m":0,"rate_m":0,"amount_m":0,"amount_cum":-2445846},{"name":"تخفیفات","unit":null,"prod_m":null,"qty_m":null,"rate_m":null,"amount_m":-310344,"amount_cum":-310344}],"month":1516301,"cum":7643076,"lastYearCum":9591327},{"period":"1404/09/30","publish":"1404/11/30","products":[{"name":"کلیه محصولات خریداری شده","unit":"عدد","prod_m":0,"qty_m":409,"rate_m":3310513,"amount_m":1354,"amount_cum":17978},{"name":"کپسول","unit":"عدد","prod_m":2300977,"qty_m":2300977,"rate_m":89005,"amount_m":204799,"amount_cum":1872272},{"name":"قرص روکش دار(دراژه)","unit":"عدد","prod_m":18558400,"qty_m":4030350,"rate_m":109163,"amount_m":439964,"amount_cum":3510623},{"name":"قرص","unit":"عدد","prod_m":5803900,"qty_m":4349282,"rate_m":96193,"amount_m":418372,"amount_cum":2883676},{"name":"قطره","unit":"شیشه","prod_m":0,"qty_m":8064,"rate_m":297743,"amount_m":2401,"amount_cum":131615},{"name":"شربت","unit":"شیشه","prod_m":86803,"qty_m":407671,"rate_m":272916,"amount_m":111260,"amount_cum":1485784},{"name":"سایر","unit":"عدد","prod_m":0,"qty_m":0,"rate_m":null,"amount_m":0,"amount_cum":2333},{"name":"قطره {کارمزدی}","unit":"شیشه","prod_m":271686,"qty_m":155366,"rate_m":381061,"amount_m":59204,"amount_cum":340594},{"name":"قرص{کارمزدی}","unit":"عدد","prod_m":11291830,"qty_m":19253390,"rate_m":4381,"amount_m":84342,"amount_cum":368812},{"name":"قرص روکش دار(دراژه)-{کارمزدی}","unit":"عدد","prod_m":22361430,"qty_m":26240370,"rate_m":4678,"amount_m":122750,"amount_cum":825505},{"name":"شربت {کارمزدی}","unit":"شیشه","prod_m":953510,"qty_m":870719,"rate_m":146090,"amount_m":127203,"amount_cum":510475},{"name":"کپسول{کارمزدی}","unit":"عدد","prod_m":768570,"qty_m":768570,"rate_m":21893,"amount_m":16826,"amount_cum":38074},{"name":"سایر(کارمزدی)","unit":"عدد","prod_m":0,"qty_m":0,"rate_m":0,"amount_m":0,"amount_cum":0},{"name":"کلیه محصولات","unit":"عدد","prod_m":null,"qty_m":0,"rate_m":0,"amount_m":0,"amount_cum":-2445846},{"name":"تخفیفات","unit":null,"prod_m":null,"qty_m":null,"rate_m":null,"amount_m":-246800,"amount_cum":-557144}],"month":1341675,"cum":8984751,"lastYearCum":11051708},{"period":"1404/10/30","publish":"1404/12/04","products":[],"month":null,"cum":null,"lastYearCum":null},{"period":"1405/01/31","publish":"1405/02/07","products":[{"name":"شربت","unit":"شیشه","prod_m":33144,"qty_m":221494,"rate_m":314713,"amount_m":69707,"amount_cum":305496},{"name":"قطره","unit":"شیشه","prod_m":0,"qty_m":5430,"rate_m":358748,"amount_m":1948,"amount_cum":7597},{"name":"قرص","unit":"عدد","prod_m":0,"qty_m":21477198,"rate_m":16433,"amount_m":352926,"amount_cum":1511385},{"name":"قرص روکش دار(دراژه)","unit":"عدد","prod_m":1950580,"qty_m":17236324,"rate_m":22532,"amount_m":388366,"amount_cum":1653166},{"name":"کپسول","unit":"عدد","prod_m":2021600,"qty_m":6559761,"rate_m":25356,"amount_m":166329,"amount_cum":686025},{"name":"کلیه محصولات خریداری شده","unit":"عدد","prod_m":0,"qty_m":3197,"rate_m":567407,"amount_m":1814,"amount_cum":5902},{"name":"سایر","unit":"عدد","prod_m":0,"qty_m":0,"rate_m":null,"amount_m":0,"amount_cum":0},{"name":"شربت {کارمزدی}","unit":"شیشه","prod_m":1036676,"qty_m":994897,"rate_m":145212,"amount_m":144471,"amount_cum":1036892},{"name":"قطره {کارمزدی}","unit":"شیشه","prod_m":105389,"qty_m":105389,"rate_m":159998,"amount_m":16862,"amount_cum":56042},{"name":"قرص{کارمزدی}","unit":"عدد","prod_m":125321290,"qty_m":152906400,"rate_m":4250,"amount_m":649798,"amount_cum":1535526},{"name":"قرص روکش دار(دراژه)-{کارمزدی}","unit":"عدد","prod_m":3091555,"qty_m":5286805,"rate_m":6409,"amount_m":33883,"amount_cum":175615},{"name":"کپسول{کارمزدی}","unit":"عدد","prod_m":10528000,"qty_m":11560220,"rate_m":3719,"amount_m":42994,"amount_cum":155270},{"name":"سایر(کارمزدی)","unit":"عدد","prod_m":0,"qty_m":0,"rate_m":0,"amount_m":0,"amount_cum":0},{"name":"کلیه محصولات","unit":"عدد","prod_m":null,"qty_m":0,"rate_m":0,"amount_m":0,"amount_cum":0},{"name":"تخفیفات","unit":null,"prod_m":null,"qty_m":null,"rate_m":null,"amount_m":-109664,"amount_cum":-522642}],"month":1759434,"cum":6606274,"lastYearCum":2625942},{"period":"1405/02/31","publish":"1405/03/05","products":[{"name":"شربت","unit":"شیشه","prod_m":298120,"qty_m":233644,"rate_m":440046,"amount_m":102814,"amount_cum":408310},{"name":"قطره","unit":"شیشه","prod_m":54544,"qty_m":13580,"rate_m":325552,"amount_m":4421,"amount_cum":11538},{"name":"قرص","unit":"عدد","prod_m":4337400,"qty_m":26203548,"rate_m":16881,"amount_m":442334,"amount_cum":2053719},{"name":"قرص روکش دار(دراژه)","unit":"عدد","prod_m":2960640,"qty_m":16392809,"rate_m":31642,"amount_m":518701,"amount_cum":2151867},{"name":"کپسول","unit":"عدد","prod_m":766800,"qty_m":3780275,"rate_m":32388,"amount_m":122436,"amount_cum":786461},{"name":"کلیه محصولات خریداری شده","unit":"عدد","prod_m":0,"qty_m":1969,"rate_m":1178263,"amount_m":2320,"amount_cum":8022},{"name":"سایر","unit":"عدد","prod_m":null,"qty_m":null,"rate_m":null,"amount_m":0,"amount_cum":0},{"name":"شربت {کارمزدی}","unit":"شیشه","prod_m":1399155,"qty_m":1367997,"rate_m":159887,"amount_m":218725,"amount_cum":1255617},{"name":"قطره {کارمزدی}","unit":"شیشه","prod_m":54958,"qty_m":54958,"rate_m":207995,"amount_m":11431,"amount_cum":67473},{"name":"قرص{کارمزدی}","unit":"عدد","prod_m":126766410,"qty_m":136715040,"rate_m":4785,"amount_m":654153,"amount_cum":2189679},{"name":"قرص روکش دار(دراژه)-{کارمزدی}","unit":"عدد","prod_m":29343840,"qty_m":30571040,"rate_m":5339,"amount_m":163217,"amount_cum":338832},{"name":"کپسول{کارمزدی}","unit":"عدد","prod_m":22596534,"qty_m":22446760,"rate_m":4000,"amount_m":89787,"amount_cum":245057},{"name":"سایر(کارمزدی)","unit":"عدد","prod_m":0,"qty_m":0,"rate_m":0,"amount_m":0,"amount_cum":0},{"name":"تخفیفات","unit":null,"prod_m":null,"qty_m":null,"rate_m":null,"amount_m":-252291,"amount_cum":-780392}],"month":2078048,"cum":8736183,"lastYearCum":3538355},{"period":"1405/03/31","publish":"1405/04/07","products":[{"name":"شربت","unit":"شیشه","prod_m":462089,"qty_m":215633,"rate_m":335630,"amount_m":72373,"amount_cum":480683},{"name":"قطره","unit":"شیشه","prod_m":192890,"qty_m":128717,"rate_m":298624,"amount_m":38438,"amount_cum":49976},{"name":"قرص","unit":"عدد","prod_m":1489400,"qty_m":18193015,"rate_m":13435,"amount_m":244426,"amount_cum":2298145},{"name":"قرص روکش دار(دراژه)","unit":"عدد","prod_m":18908860,"qty_m":13734874,"rate_m":21088,"amount_m":289642,"amount_cum":2441509},{"name":"کپسول","unit":"عدد","prod_m":2423400,"qty_m":4659643,"rate_m":44899,"amount_m":209214,"amount_cum":995675},{"name":"کلیه محصولات خریداری شده","unit":"عدد","prod_m":null,"qty_m":779,"rate_m":1920411,"amount_m":1496,"amount_cum":9518},{"name":"سایر","unit":"عدد","prod_m":null,"qty_m":null,"rate_m":null,"amount_m":0,"amount_cum":0},{"name":"شربت {کارمزدی}","unit":"شیشه","prod_m":1231765,"qty_m":1304042,"rate_m":159725,"amount_m":208288,"amount_cum":1463905},{"name":"قطره {کارمزدی}","unit":"شیشه","prod_m":0,"qty_m":0,"rate_m":0,"amount_m":0,"amount_cum":67473},{"name":"قرص{کارمزدی}","unit":"عدد","prod_m":162784920,"qty_m":163989060,"rate_m":5472,"amount_m":897282,"amount_cum":3086961},{"name":"قرص روکش دار(دراژه)-{کارمزدی}","unit":"عدد","prod_m":66729810,"qty_m":76132770,"rate_m":7376,"amount_m":561537,"amount_cum":900369},{"name":"کپسول{کارمزدی}","unit":"عدد","prod_m":6123130,"qty_m":2421390,"rate_m":5833,"amount_m":14123,"amount_cum":259180},{"name":"سایر(کارمزدی)","unit":"عدد","prod_m":0,"qty_m":0,"rate_m":0,"amount_m":0,"amount_cum":0},{"name":"تخفیفات","unit":null,"prod_m":null,"qty_m":null,"rate_m":null,"amount_m":-297438,"amount_cum":-1077830}],"month":2239381,"cum":10975564,"lastYearCum":4571979}],"quarters":[{"period":"1404/03/31","months":3,"audited":false,"consolidated":false,"publish":"1404/04/30","revenue":1613756,"revenue_ly":3176178,"gross":617007,"gross_ly":1318683,"net":-213885,"net_ly":435165,"eps":-39,"eps_ly":79,"capital":5500000,"capital_ly":5500000},{"period":"1404/06/31","months":6,"audited":false,"consolidated":false,"publish":"1404/08/04","revenue":4571979,"revenue_ly":6911162,"gross":1731305,"gross_ly":2706851,"net":-11290,"net_ly":857337,"eps":-2,"eps_ly":156,"capital":5500000,"capital_ly":5500000},{"period":"1404/09/30","months":9,"audited":false,"consolidated":true,"publish":"1404/12/06","revenue":8984751,"revenue_ly":11051708,"gross":3734893,"gross_ly":4330856,"net":829895,"net_ly":1506832,"eps":91,"eps_ly":274},{"period":"1404/12/29","months":3,"audited":false,"consolidated":false,"publish":"1405/03/13","revenue":4881624,"revenue_ly":1613756,"gross":2175043,"gross_ly":617007,"net":812811,"net_ly":-213924,"eps":89,"eps_ly":-39,"capital":9130000,"capital_ly":5500000}]}