{"symbol":"دسبحان","updated":"2026-07-07T18:05:50.192Z","months":[{"period":"1404/01/31","publish":"1404/02/06","products":[{"name":"قرص و دراژه.","unit":"هزار عدد","prod_m":128064,"qty_m":245980,"rate_m":9799675,"amount_m":2410524,"amount_cum":6935576},{"name":"کپسول","unit":"هزار عدد","prod_m":1738,"qty_m":6111,"rate_m":11913926,"amount_m":72806,"amount_cum":225130},{"name":"پماد و کرم","unit":"هزار تیوپ","prod_m":531,"qty_m":610,"rate_m":356295082,"amount_m":217340,"amount_cum":1199606},{"name":"قطره","unit":"هزار شیشه","prod_m":12,"qty_m":54,"rate_m":153574074,"amount_m":8293,"amount_cum":27105},{"name":"قرص و دراژه.","unit":"هزار عدد","prod_m":0,"qty_m":0,"rate_m":0,"amount_m":0,"amount_cum":69207},{"name":"پماد و کرم","unit":"هزار تیوپ","prod_m":30,"qty_m":30,"rate_m":240000000,"amount_m":7200,"amount_cum":39670},{"name":"قطره","unit":"هزار شیشه","prod_m":0,"qty_m":0,"rate_m":0,"amount_m":0,"amount_cum":0},{"name":"پماد و کرم","unit":"هزار تیوپ","prod_m":null,"qty_m":null,"rate_m":0,"amount_m":0,"amount_cum":0},{"name":"قرص و دراژه.","unit":"هزار عدد","prod_m":null,"qty_m":null,"rate_m":0,"amount_m":0,"amount_cum":0},{"name":"کپسول","unit":"هزار عدد","prod_m":null,"qty_m":null,"rate_m":0,"amount_m":0,"amount_cum":12003},{"name":"قطره","unit":"هزار شیشه","prod_m":null,"qty_m":-42,"rate_m":119761905,"amount_m":-5030,"amount_cum":-7867},{"name":"کپسول","unit":"هزار عدد","prod_m":null,"qty_m":-94,"rate_m":15851064,"amount_m":-1490,"amount_cum":-25488},{"name":"پماد و کرم","unit":"هزار تیوپ","prod_m":null,"qty_m":0,"rate_m":0,"amount_m":0,"amount_cum":-45776},{"name":"قرص و دراژه.","unit":"هزار عدد","prod_m":null,"qty_m":-111950,"rate_m":6789897,"amount_m":-760129,"amount_cum":-914044},{"name":"تخفیفات","unit":null,"prod_m":null,"qty_m":null,"rate_m":null,"amount_m":-182099,"amount_cum":-665326}],"month":1767415,"cum":6849796,"lastYearCum":4973305},{"period":"1404/03/31","publish":"1404/07/01","products":[{"name":"قرص و دراژه.","unit":"هزار عدد","prod_m":318236,"qty_m":309510,"rate_m":7387257,"amount_m":2286430,"amount_cum":11377128},{"name":"کپسول","unit":"هزار عدد","prod_m":9546,"qty_m":7071,"rate_m":11590864,"amount_m":81959,"amount_cum":505135},{"name":"پماد و کرم","unit":"هزار تیوپ","prod_m":1558,"qty_m":1214,"rate_m":321918451,"amount_m":390809,"amount_cum":1984051},{"name":"قطره","unit":"هزار شیشه","prod_m":24,"qty_m":0,"rate_m":null,"amount_m":183,"amount_cum":30916},{"name":"قرص و دراژه.","unit":"هزار عدد","prod_m":487,"qty_m":487,"rate_m":2470226,"amount_m":1203,"amount_cum":70410},{"name":"پماد و کرم","unit":"هزار تیوپ","prod_m":52,"qty_m":52,"rate_m":137538462,"amount_m":7152,"amount_cum":46822},{"name":"قطره","unit":"هزار شیشه","prod_m":0,"qty_m":0,"rate_m":0,"amount_m":0,"amount_cum":0},{"name":"پماد و کرم","unit":"هزار تیوپ","prod_m":0,"qty_m":0,"rate_m":0,"amount_m":0,"amount_cum":0},{"name":"قرص و دراژه.","unit":"هزار عدد","prod_m":0,"qty_m":0,"rate_m":0,"amount_m":0,"amount_cum":0},{"name":"کپسول","unit":"هزار عدد","prod_m":1466,"qty_m":1466,"rate_m":2800136,"amount_m":4105,"amount_cum":16108},{"name":"قطره","unit":"هزار شیشه","prod_m":null,"qty_m":-1,"rate_m":164000000,"amount_m":-164,"amount_cum":-9298},{"name":"کپسول","unit":"هزار عدد","prod_m":null,"qty_m":0,"rate_m":0,"amount_m":0,"amount_cum":-27063},{"name":"پماد و کرم","unit":"هزار تیوپ","prod_m":null,"qty_m":-15,"rate_m":316800000,"amount_m":-4752,"amount_cum":-74615},{"name":"قرص و دراژه.","unit":"هزار عدد","prod_m":null,"qty_m":-5745,"rate_m":8581549,"amount_m":-49301,"amount_cum":-1119744},{"name":"تخفیفات","unit":null,"prod_m":null,"qty_m":null,"rate_m":null,"amount_m":-359323,"amount_cum":-1341382}],"month":2358301,"cum":11458468,"lastYearCum":8644021},{"period":"1404/04/31","publish":"1404/07/07","products":[{"name":"قرص و دراژه.","unit":"هزار عدد","prod_m":244426,"qty_m":303059,"rate_m":8010589,"amount_m":2427681,"amount_cum":13804809},{"name":"کپسول","unit":"هزار عدد","prod_m":10995,"qty_m":11966,"rate_m":15368377,"amount_m":183898,"amount_cum":689033},{"name":"پماد و کرم","unit":"هزار تیوپ","prod_m":1096,"qty_m":1646,"rate_m":348156744,"amount_m":573066,"amount_cum":2557117},{"name":"قطره","unit":"هزار شیشه","prod_m":84,"qty_m":67,"rate_m":152059701,"amount_m":10188,"amount_cum":41104},{"name":"قرص و دراژه.","unit":"هزار عدد","prod_m":94,"qty_m":94,"rate_m":4978723,"amount_m":468,"amount_cum":70878},{"name":"پماد و کرم","unit":"هزار تیوپ","prod_m":0,"qty_m":0,"rate_m":null,"amount_m":66,"amount_cum":46888},{"name":"قطره","unit":"هزار شیشه","prod_m":0,"qty_m":13,"rate_m":79076923,"amount_m":1028,"amount_cum":1028},{"name":"پماد و کرم","unit":"هزار تیوپ","prod_m":0,"qty_m":0,"rate_m":null,"amount_m":1677,"amount_cum":1677},{"name":"قرص و دراژه.","unit":"هزار عدد","prod_m":0,"qty_m":0,"rate_m":0,"amount_m":0,"amount_cum":0},{"name":"کپسول","unit":"هزار عدد","prod_m":0,"qty_m":0,"rate_m":0,"amount_m":0,"amount_cum":16108},{"name":"قطره","unit":"هزار شیشه","prod_m":null,"qty_m":0,"rate_m":0,"amount_m":0,"amount_cum":-9298},{"name":"کپسول","unit":"هزار عدد","prod_m":null,"qty_m":0,"rate_m":0,"amount_m":0,"amount_cum":-27063},{"name":"پماد و کرم","unit":"هزار تیوپ","prod_m":null,"qty_m":0,"rate_m":0,"amount_m":0,"amount_cum":-74615},{"name":"قرص و دراژه.","unit":"هزار عدد","prod_m":null,"qty_m":-3467,"rate_m":7510528,"amount_m":-26039,"amount_cum":-1145783},{"name":"تخفیفات","unit":null,"prod_m":null,"qty_m":null,"rate_m":null,"amount_m":-65646,"amount_cum":-1407028}],"month":3106387,"cum":14564855,"lastYearCum":10545122},{"period":"1404/05/31","publish":"1404/07/07","products":[{"name":"قرص و دراژه.","unit":"هزار عدد","prod_m":278459,"qty_m":324169,"rate_m":8297262,"amount_m":2689715,"amount_cum":16494524},{"name":"کپسول","unit":"هزار عدد","prod_m":4321,"qty_m":4475,"rate_m":15285587,"amount_m":68403,"amount_cum":757436},{"name":"پماد و کرم","unit":"هزار تیوپ","prod_m":1284,"qty_m":1229,"rate_m":338924329,"amount_m":416538,"amount_cum":2973655},{"name":"قطره","unit":"هزار شیشه","prod_m":74,"qty_m":91,"rate_m":153241758,"amount_m":13945,"amount_cum":55049},{"name":"قرص و دراژه.","unit":"هزار عدد","prod_m":22723,"qty_m":22723,"rate_m":3389121,"amount_m":77011,"amount_cum":147889},{"name":"پماد و کرم","unit":"هزار تیوپ","prod_m":232,"qty_m":232,"rate_m":166612069,"amount_m":38654,"amount_cum":85542},{"name":"قطره","unit":"هزار شیشه","prod_m":0,"qty_m":0,"rate_m":0,"amount_m":0,"amount_cum":1028},{"name":"پماد و کرم","unit":"هزار تیوپ","prod_m":26,"qty_m":26,"rate_m":66230769,"amount_m":1722,"amount_cum":3399},{"name":"قرص و دراژه.","unit":"هزار عدد","prod_m":0,"qty_m":0,"rate_m":0,"amount_m":0,"amount_cum":0},{"name":"کپسول","unit":"هزار عدد","prod_m":0,"qty_m":0,"rate_m":0,"amount_m":0,"amount_cum":16108},{"name":"قطره","unit":"هزار شیشه","prod_m":null,"qty_m":-1,"rate_m":165000000,"amount_m":-165,"amount_cum":-9463},{"name":"کپسول","unit":"هزار عدد","prod_m":null,"qty_m":0,"rate_m":0,"amount_m":0,"amount_cum":-27063},{"name":"پماد و کرم","unit":"هزار تیوپ","prod_m":null,"qty_m":-15,"rate_m":316733333,"amount_m":-4751,"amount_cum":-79366},{"name":"قرص و دراژه.","unit":"هزار عدد","prod_m":null,"qty_m":-2414,"rate_m":8937034,"amount_m":-21574,"amount_cum":-1167357},{"name":"تخفیفات","unit":null,"prod_m":null,"qty_m":null,"rate_m":null,"amount_m":-163257,"amount_cum":-1570285}],"month":3116241,"cum":17681096,"lastYearCum":13248300},{"period":"1404/07/30","publish":"1404/08/07","products":[{"name":"قرص و دراژه.","unit":"هزار عدد","prod_m":379644,"qty_m":379463,"rate_m":7418138,"amount_m":2814909,"amount_cum":21929637},{"name":"کپسول","unit":"هزار عدد","prod_m":7642,"qty_m":7639,"rate_m":15245320,"amount_m":116459,"amount_cum":877202},{"name":"پماد و کرم","unit":"هزار تیوپ","prod_m":1651,"qty_m":1641,"rate_m":384561853,"amount_m":631066,"amount_cum":4182011},{"name":"قطره","unit":"هزار شیشه","prod_m":0,"qty_m":0,"rate_m":null,"amount_m":0,"amount_cum":64153},{"name":"قرص و دراژه.","unit":"هزار عدد","prod_m":9015,"qty_m":9015,"rate_m":5053023,"amount_m":45553,"amount_cum":196237},{"name":"پماد و کرم","unit":"هزار تیوپ","prod_m":0,"qty_m":0,"rate_m":0,"amount_m":0,"amount_cum":85542},{"name":"قطره","unit":"هزار شیشه","prod_m":15,"qty_m":15,"rate_m":76466667,"amount_m":1147,"amount_cum":3626},{"name":"پماد و کرم","unit":"هزار تیوپ","prod_m":0,"qty_m":0,"rate_m":0,"amount_m":0,"amount_cum":3399},{"name":"قرص و دراژه.","unit":"هزار عدد","prod_m":756,"qty_m":756,"rate_m":3798942,"amount_m":2872,"amount_cum":17408},{"name":"کپسول","unit":"هزار عدد","prod_m":0,"qty_m":0,"rate_m":0,"amount_m":0,"amount_cum":24842},{"name":"قطره","unit":"هزار شیشه","prod_m":null,"qty_m":0,"rate_m":0,"amount_m":0,"amount_cum":-9463},{"name":"کپسول","unit":"هزار عدد","prod_m":null,"qty_m":0,"rate_m":0,"amount_m":0,"amount_cum":-27063},{"name":"پماد و کرم","unit":"هزار تیوپ","prod_m":null,"qty_m":-184,"rate_m":423521739,"amount_m":-77928,"amount_cum":-157294},{"name":"قرص و دراژه.","unit":"هزار عدد","prod_m":null,"qty_m":-64974,"rate_m":6345569,"amount_m":-412297,"amount_cum":-1579713},{"name":"تخفیفات","unit":null,"prod_m":null,"qty_m":null,"rate_m":null,"amount_m":-3219,"amount_cum":-1693648}],"month":3118562,"cum":23916876,"lastYearCum":14465690},{"period":"1404/09/30","publish":"1404/10/07","products":[{"name":"قرص و دراژه.","unit":"هزار عدد","prod_m":221105,"qty_m":183402,"rate_m":15967890,"amount_m":2928543,"amount_cum":28197306},{"name":"کپسول","unit":"هزار عدد","prod_m":10515,"qty_m":8445,"rate_m":16751095,"amount_m":141463,"amount_cum":1356729},{"name":"پماد و کرم","unit":"هزار تیوپ","prod_m":1130,"qty_m":958,"rate_m":744919624,"amount_m":713633,"amount_cum":5512489},{"name":"قطره","unit":"هزار شیشه","prod_m":0,"qty_m":0,"rate_m":null,"amount_m":0,"amount_cum":64153},{"name":"قرص و دراژه.","unit":"هزار عدد","prod_m":14,"qty_m":14,"rate_m":13857143,"amount_m":194,"amount_cum":221756},{"name":"پماد و کرم","unit":"هزار تیوپ","prod_m":0,"qty_m":0,"rate_m":0,"amount_m":0,"amount_cum":108935},{"name":"قطره","unit":"هزار شیشه","prod_m":19,"qty_m":19,"rate_m":77105263,"amount_m":1465,"amount_cum":10782},{"name":"پماد و کرم","unit":"هزار تیوپ","prod_m":0,"qty_m":0,"rate_m":0,"amount_m":0,"amount_cum":3399},{"name":"قرص و دراژه.","unit":"هزار عدد","prod_m":0,"qty_m":0,"rate_m":0,"amount_m":0,"amount_cum":26833},{"name":"کپسول","unit":"هزار عدد","prod_m":0,"qty_m":0,"rate_m":0,"amount_m":0,"amount_cum":28278},{"name":"قطره","unit":"هزار شیشه","prod_m":null,"qty_m":-8164,"rate_m":13482117,"amount_m":-110068,"amount_cum":-126350},{"name":"کپسول","unit":"هزار عدد","prod_m":null,"qty_m":-1332,"rate_m":13630631,"amount_m":-18156,"amount_cum":-45935},{"name":"پماد و کرم","unit":"هزار تیوپ","prod_m":null,"qty_m":-6,"rate_m":103166667,"amount_m":-619,"amount_cum":-236638},{"name":"قرص و دراژه.","unit":"هزار عدد","prod_m":null,"qty_m":0,"rate_m":0,"amount_m":0,"amount_cum":-2353435},{"name":"تخفیفات","unit":null,"prod_m":null,"qty_m":null,"rate_m":null,"amount_m":-570230,"amount_cum":-2628055}],"month":3086225,"cum":30140247,"lastYearCum":17972069},{"period":"1404/10/30","publish":"1404/11/06","products":[],"month":null,"cum":null,"lastYearCum":null},{"period":"1404/11/30","publish":"1404/12/06","products":[{"name":"قرص و دراژه.","unit":"هزار عدد","prod_m":199771,"qty_m":165330,"rate_m":11145243,"amount_m":1842643,"amount_cum":4845535},{"name":"کپسول","unit":"هزار عدد","prod_m":11360,"qty_m":14013,"rate_m":14579961,"amount_m":204309,"amount_cum":329874},{"name":"پماد و کرم","unit":"هزار تیوپ","prod_m":1274,"qty_m":924,"rate_m":663354978,"amount_m":612940,"amount_cum":1151115},{"name":"قطره","unit":"هزار شیشه","prod_m":61,"qty_m":149,"rate_m":218919463,"amount_m":32619,"amount_cum":37207},{"name":"قرص و دراژه.","unit":"هزار عدد","prod_m":1242,"qty_m":1242,"rate_m":16301127,"amount_m":20246,"amount_cum":20246},{"name":"کپسول","unit":"هزار عدد","prod_m":1020,"qty_m":1020,"rate_m":25807843,"amount_m":26324,"amount_cum":26324},{"name":"پماد و کرم","unit":"هزار تیوپ","prod_m":75,"qty_m":75,"rate_m":323280000,"amount_m":24246,"amount_cum":24246},{"name":"قطره","unit":"هزار شیشه","prod_m":81,"qty_m":81,"rate_m":78111111,"amount_m":6327,"amount_cum":6327},{"name":"پماد و کرم","unit":"هزار تیوپ","prod_m":0,"qty_m":0,"rate_m":0,"amount_m":0,"amount_cum":0},{"name":"قرص و دراژه.","unit":"هزار عدد","prod_m":0,"qty_m":0,"rate_m":0,"amount_m":0,"amount_cum":0},{"name":"کپسول","unit":"هزار عدد","prod_m":380,"qty_m":380,"rate_m":3994737,"amount_m":1518,"amount_cum":2706},{"name":"قطره","unit":"هزار شیشه","prod_m":null,"qty_m":0,"rate_m":0,"amount_m":0,"amount_cum":0},{"name":"کپسول","unit":"هزار عدد","prod_m":null,"qty_m":-250,"rate_m":18648000,"amount_m":-4662,"amount_cum":-10878},{"name":"پماد و کرم","unit":"هزار تیوپ","prod_m":null,"qty_m":0,"rate_m":0,"amount_m":0,"amount_cum":0},{"name":"قرص و دراژه.","unit":"هزار عدد","prod_m":null,"qty_m":-4613,"rate_m":11451550,"amount_m":-52826,"amount_cum":-53426},{"name":"تخفیفات","unit":null,"prod_m":null,"qty_m":null,"rate_m":null,"amount_m":-202733,"amount_cum":-419938}],"month":2510951,"cum":5959338,"lastYearCum":3328694},{"period":"1405/01/31","publish":"1405/02/07","products":[{"name":"قرص و دراژه.","unit":"هزار عدد","prod_m":81157,"qty_m":114844,"rate_m":22427075,"amount_m":2575615,"amount_cum":9662198},{"name":"کپسول","unit":"هزار عدد","prod_m":1521,"qty_m":568,"rate_m":48024648,"amount_m":27278,"amount_cum":380424},{"name":"پماد و کرم","unit":"هزار تیوپ","prod_m":490,"qty_m":316,"rate_m":969158228,"amount_m":306254,"amount_cum":1991591},{"name":"قطره","unit":"هزار شیشه","prod_m":54,"qty_m":0,"rate_m":null,"amount_m":0,"amount_cum":37207},{"name":"قرص و دراژه.","unit":"هزار عدد","prod_m":0,"qty_m":0,"rate_m":0,"amount_m":0,"amount_cum":20246},{"name":"کپسول","unit":"هزار عدد","prod_m":0,"qty_m":0,"rate_m":0,"amount_m":0,"amount_cum":26324},{"name":"پماد و کرم","unit":"هزار تیوپ","prod_m":0,"qty_m":0,"rate_m":0,"amount_m":0,"amount_cum":24246},{"name":"قطره","unit":"هزار شیشه","prod_m":0,"qty_m":0,"rate_m":0,"amount_m":0,"amount_cum":7903},{"name":"پماد و کرم","unit":"هزار تیوپ","prod_m":0,"qty_m":0,"rate_m":0,"amount_m":0,"amount_cum":0},{"name":"قرص و دراژه.","unit":"هزار عدد","prod_m":0,"qty_m":0,"rate_m":0,"amount_m":0,"amount_cum":0},{"name":"کپسول","unit":"هزار عدد","prod_m":674,"qty_m":674,"rate_m":3998516,"amount_m":2695,"amount_cum":5401},{"name":"قطره","unit":"هزار شیشه","prod_m":null,"qty_m":0,"rate_m":0,"amount_m":0,"amount_cum":0},{"name":"کپسول","unit":"هزار عدد","prod_m":null,"qty_m":0,"rate_m":0,"amount_m":0,"amount_cum":-10878},{"name":"پماد و کرم","unit":"هزار تیوپ","prod_m":null,"qty_m":0,"rate_m":0,"amount_m":0,"amount_cum":0},{"name":"قرص و دراژه.","unit":"هزار عدد","prod_m":null,"qty_m":0,"rate_m":0,"amount_m":0,"amount_cum":-191631},{"name":"تخفیفات","unit":null,"prod_m":null,"qty_m":null,"rate_m":null,"amount_m":-389505,"amount_cum":-959791}],"month":2522337,"cum":10993240,"lastYearCum":6849796},{"period":"1405/02/31","publish":"1405/03/09","products":[{"name":"قرص و دراژه.","unit":"هزار عدد","prod_m":285956,"qty_m":279907,"rate_m":21728617,"amount_m":6081992,"amount_cum":15744190},{"name":"کپسول","unit":"هزار عدد","prod_m":8725,"qty_m":4083,"rate_m":28308107,"amount_m":115582,"amount_cum":496006},{"name":"پماد و کرم","unit":"هزار تیوپ","prod_m":957,"qty_m":1306,"rate_m":865632466,"amount_m":1130516,"amount_cum":3122107},{"name":"قطره","unit":"هزار شیشه","prod_m":90,"qty_m":101,"rate_m":322138614,"amount_m":32536,"amount_cum":69743},{"name":"قرص و دراژه.","unit":"هزار عدد","prod_m":6950,"qty_m":6950,"rate_m":26408777,"amount_m":183541,"amount_cum":203787},{"name":"کپسول","unit":"هزار عدد","prod_m":0,"qty_m":0,"rate_m":0,"amount_m":0,"amount_cum":26324},{"name":"پماد و کرم","unit":"هزار تیوپ","prod_m":0,"qty_m":0,"rate_m":0,"amount_m":0,"amount_cum":24246},{"name":"قطره","unit":"هزار شیشه","prod_m":92,"qty_m":92,"rate_m":90326087,"amount_m":8310,"amount_cum":16213},{"name":"پماد و کرم","unit":"هزار تیوپ","prod_m":0,"qty_m":0,"rate_m":0,"amount_m":0,"amount_cum":0},{"name":"قرص و دراژه.","unit":"هزار عدد","prod_m":221,"qty_m":221,"rate_m":2095023,"amount_m":463,"amount_cum":463},{"name":"کپسول","unit":"هزار عدد","prod_m":1460,"qty_m":1460,"rate_m":4550685,"amount_m":6644,"amount_cum":12045},{"name":"قطره","unit":"هزار شیشه","prod_m":null,"qty_m":0,"rate_m":0,"amount_m":0,"amount_cum":0},{"name":"کپسول","unit":"هزار عدد","prod_m":null,"qty_m":10,"rate_m":-12200000,"amount_m":-122,"amount_cum":-11000},{"name":"پماد و کرم","unit":"هزار تیوپ","prod_m":null,"qty_m":0,"rate_m":0,"amount_m":0,"amount_cum":0},{"name":"قرص و دراژه.","unit":"هزار عدد","prod_m":null,"qty_m":47,"rate_m":-20212766,"amount_m":-950,"amount_cum":-192581},{"name":"تخفیفات","unit":null,"prod_m":null,"qty_m":null,"rate_m":null,"amount_m":-358384,"amount_cum":-1318175}],"month":7200128,"cum":18193368,"lastYearCum":9765493}],"quarters":[{"period":"1403/12/30","months":3,"audited":false,"consolidated":false,"publish":"1404/01/30","revenue":5082381,"revenue_ly":3215158,"gross":2218378,"gross_ly":966596,"net":925697,"net_ly":319147,"eps":0,"eps_ly":0,"capital":6820000,"capital_ly":5330000},{"period":"1404/03/31","months":6,"audited":true,"consolidated":false,"publish":"1404/07/01","revenue":11458468,"revenue_ly":8644021,"gross":5008196,"gross_ly":3421141,"net":1681589,"net_ly":1178080,"eps":247,"eps_ly":221,"capital":6820000,"capital_ly":5330000},{"period":"1404/06/31","months":9,"audited":false,"consolidated":false,"publish":"1404/07/29","revenue":20798314,"revenue_ly":13433305,"gross":9679114,"gross_ly":5202447,"net":3635759,"net_ly":2899939,"eps":364,"eps_ly":544,"capital":10000000,"capital_ly":5330000},{"period":"1404/12/29","months":3,"audited":false,"consolidated":false,"publish":"1405/01/30","revenue":8470903,"revenue_ly":5082381,"gross":4442599,"gross_ly":2218378,"net":1778022,"net_ly":925697,"eps":178,"eps_ly":93,"capital":10000000,"capital_ly":10000000}]}