{"symbol":"دکیمی","updated":"2026-07-07T17:41:27.931Z","months":[{"period":"1403/12/30","publish":"1404/01/09","products":[{"name":"تولید قراردادی","unit":"کیلوگرم","prod_m":null,"qty_m":null,"rate_m":null,"amount_m":0,"amount_cum":0},{"name":"کپسول","unit":"صد عددی","prod_m":null,"qty_m":15434,"rate_m":1029156,"amount_m":15884,"amount_cum":144677},{"name":"قطره","unit":"عدد","prod_m":null,"qty_m":8000,"rate_m":133250,"amount_m":1066,"amount_cum":4897},{"name":"آمپول","unit":"عدد","prod_m":2751805,"qty_m":4632431,"rate_m":35971,"amount_m":166635,"amount_cum":550006},{"name":"سوسپانسیون","unit":"شیشه","prod_m":null,"qty_m":4060,"rate_m":208128,"amount_m":845,"amount_cum":51422},{"name":"محصولات شیمیایی","unit":"کیلوگرم","prod_m":111200,"qty_m":122300,"rate_m":794669,"amount_m":97188,"amount_cum":288067},{"name":"قرص و دراژه","unit":"صد عددی","prod_m":445045,"qty_m":366338,"rate_m":649032,"amount_m":237765,"amount_cum":956439},{"name":"قرص و دراژه","unit":"صد عددی","prod_m":null,"qty_m":null,"rate_m":0,"amount_m":0,"amount_cum":0},{"name":"تخفیفات","unit":null,"prod_m":null,"qty_m":null,"rate_m":null,"amount_m":0,"amount_cum":0}],"month":519383,"cum":1995508,"lastYearCum":2430172},{"period":"1404/01/31","publish":"1404/02/06","products":[{"name":"قرص و دراژه","unit":"صد عددی","prod_m":400690,"qty_m":408872,"rate_m":930538,"amount_m":380471,"amount_cum":1419705},{"name":"محصولات شیمیایی","unit":"کیلوگرم","prod_m":153000,"qty_m":55200,"rate_m":729330,"amount_m":40259,"amount_cum":341646},{"name":"سوسپانسیون","unit":"شیشه","prod_m":0,"qty_m":0,"rate_m":null,"amount_m":0,"amount_cum":55857},{"name":"آمپول","unit":"عدد","prod_m":1480100,"qty_m":634810,"rate_m":221019,"amount_m":140305,"amount_cum":738455},{"name":"قطره","unit":"عدد","prod_m":null,"qty_m":17060,"rate_m":119050,"amount_m":2031,"amount_cum":6968},{"name":"کپسول","unit":"صد عددی","prod_m":9813,"qty_m":12794,"rate_m":2959043,"amount_m":37858,"amount_cum":192326},{"name":"تولید قراردادی","unit":"کیلوگرم","prod_m":null,"qty_m":null,"rate_m":null,"amount_m":0,"amount_cum":0},{"name":"قرص و دراژه","unit":"صد عددی","prod_m":null,"qty_m":null,"rate_m":0,"amount_m":0,"amount_cum":0},{"name":"تخفیفات","unit":null,"prod_m":null,"qty_m":null,"rate_m":null,"amount_m":-57927,"amount_cum":-216452}],"month":542997,"cum":2538505,"lastYearCum":2899266},{"period":"1404/02/31","publish":"1404/03/06","products":[{"name":"قرص و دراژه","unit":"صد عددی","prod_m":519554,"qty_m":669007,"rate_m":820820,"amount_m":549134,"amount_cum":1968839},{"name":"محصولات شیمیایی","unit":"کیلوگرم","prod_m":67400,"qty_m":70926,"rate_m":852720,"amount_m":60480,"amount_cum":402126},{"name":"سوسپانسیون","unit":"شیشه","prod_m":0,"qty_m":0,"rate_m":null,"amount_m":0,"amount_cum":55857},{"name":"آمپول","unit":"عدد","prod_m":1395310,"qty_m":1487670,"rate_m":228656,"amount_m":340164,"amount_cum":1078619},{"name":"قطره","unit":"عدد","prod_m":0,"qty_m":22080,"rate_m":141440,"amount_m":3123,"amount_cum":10091},{"name":"کپسول","unit":"صد عددی","prod_m":0,"qty_m":32626,"rate_m":1003678,"amount_m":32746,"amount_cum":225072},{"name":"تولید قراردادی","unit":"کیلوگرم","prod_m":0,"qty_m":0,"rate_m":null,"amount_m":0,"amount_cum":0},{"name":"آمپول","unit":"عدد","prod_m":0,"qty_m":0,"rate_m":0,"amount_m":0,"amount_cum":0},{"name":"قرص و دراژه","unit":"صد عددی","prod_m":null,"qty_m":0,"rate_m":0,"amount_m":0,"amount_cum":-3264},{"name":"تخفیفات","unit":null,"prod_m":null,"qty_m":null,"rate_m":null,"amount_m":-109850,"amount_cum":-326302}],"month":875797,"cum":3411038,"lastYearCum":3728669},{"period":"1404/03/31","publish":"1404/04/17","products":[{"name":"قرص و دراژه","unit":"صد عددی","prod_m":399125,"qty_m":702902,"rate_m":695673,"amount_m":488990,"amount_cum":2471146},{"name":"محصولات شیمیایی","unit":"کیلوگرم","prod_m":44800,"qty_m":19600,"rate_m":980408,"amount_m":19216,"amount_cum":421342},{"name":"سوسپانسیون","unit":"شیشه","prod_m":null,"qty_m":6010,"rate_m":276040,"amount_m":1659,"amount_cum":57516},{"name":"آمپول","unit":"عدد","prod_m":2055375,"qty_m":1452385,"rate_m":102007,"amount_m":148153,"amount_cum":1230370},{"name":"قطره","unit":"عدد","prod_m":null,"qty_m":20745,"rate_m":152326,"amount_m":3160,"amount_cum":13251},{"name":"کپسول","unit":"صد عددی","prod_m":8291,"qty_m":43444,"rate_m":974588,"amount_m":42340,"amount_cum":267412},{"name":"تولید قراردادی","unit":"کیلوگرم","prod_m":null,"qty_m":null,"rate_m":null,"amount_m":0,"amount_cum":0},{"name":"آمپول","unit":"عدد","prod_m":null,"qty_m":null,"rate_m":0,"amount_m":0,"amount_cum":0},{"name":"قرص و دراژه","unit":"صد عددی","prod_m":null,"qty_m":-195985,"rate_m":460770,"amount_m":-90304,"amount_cum":-106885},{"name":"تخفیفات","unit":null,"prod_m":null,"qty_m":null,"rate_m":null,"amount_m":-63373,"amount_cum":-389675}],"month":549841,"cum":3960879,"lastYearCum":4104429},{"period":"1404/04/30","publish":"1404/05/06","products":[{"name":"قرص و دراژه","unit":"صد عددی","prod_m":682615,"qty_m":645101,"rate_m":1037585,"amount_m":669347,"amount_cum":3140493},{"name":"محصولات شیمیایی","unit":"کیلوگرم","prod_m":73600,"qty_m":60800,"rate_m":930921,"amount_m":56600,"amount_cum":477942},{"name":"سوسپانسیون","unit":"شیشه","prod_m":null,"qty_m":7070,"rate_m":275955,"amount_m":1951,"amount_cum":59467},{"name":"آمپول","unit":"عدد","prod_m":2518217,"qty_m":1972622,"rate_m":60167,"amount_m":118686,"amount_cum":1349056},{"name":"قطره","unit":"عدد","prod_m":null,"qty_m":212013,"rate_m":160000,"amount_m":33922,"amount_cum":47173},{"name":"کپسول","unit":"صد عددی","prod_m":39186,"qty_m":84849,"rate_m":1104433,"amount_m":93710,"amount_cum":361122},{"name":"تولید قراردادی","unit":"کیلوگرم","prod_m":null,"qty_m":null,"rate_m":null,"amount_m":0,"amount_cum":0},{"name":"آمپول","unit":"عدد","prod_m":null,"qty_m":200000,"rate_m":130000,"amount_m":26000,"amount_cum":26000},{"name":"تخفیفات","unit":null,"prod_m":null,"qty_m":null,"rate_m":null,"amount_m":-99443,"amount_cum":-489118}],"month":900773,"cum":4861652,"lastYearCum":4603951},{"period":"1404/06/31","publish":"1404/07/06","products":[{"name":"قرص و دراژه","unit":"صد عددی","prod_m":653757,"qty_m":1063639,"rate_m":844363,"amount_m":898097,"amount_cum":4695807},{"name":"محصولات شیمیایی","unit":"کیلوگرم","prod_m":19800,"qty_m":55600,"rate_m":927716,"amount_m":51581,"amount_cum":547137},{"name":"سوسپانسیون","unit":"شیشه","prod_m":0,"qty_m":0,"rate_m":null,"amount_m":0,"amount_cum":61966},{"name":"آمپول","unit":"عدد","prod_m":2354394,"qty_m":1866390,"rate_m":113911,"amount_m":212602,"amount_cum":1915751},{"name":"قطره","unit":"عدد","prod_m":0,"qty_m":0,"rate_m":null,"amount_m":0,"amount_cum":47173},{"name":"کپسول","unit":"صد عددی","prod_m":32433,"qty_m":47820,"rate_m":1008762,"amount_m":48239,"amount_cum":560192},{"name":"تولید قراردادی","unit":"کیلوگرم","prod_m":null,"qty_m":null,"rate_m":null,"amount_m":0,"amount_cum":0},{"name":"آمپول","unit":"عدد","prod_m":null,"qty_m":0,"rate_m":0,"amount_m":0,"amount_cum":48500},{"name":"قرص و دراژه","unit":"صد عددی","prod_m":null,"qty_m":-25573,"rate_m":461893,"amount_m":-11812,"amount_cum":-137047},{"name":"آمپول","unit":"عدد","prod_m":null,"qty_m":-24870,"rate_m":73341,"amount_m":-1824,"amount_cum":-5422},{"name":"تخفیفات","unit":null,"prod_m":null,"qty_m":null,"rate_m":null,"amount_m":-96071,"amount_cum":-694044}],"month":1100812,"cum":7034369,"lastYearCum":5257260},{"period":"1404/07/30","publish":"1404/08/06","products":[{"name":"قرص و دراژه","unit":"صد عددی","prod_m":661022,"qty_m":689897,"rate_m":987979,"amount_m":681604,"amount_cum":5377411},{"name":"محصولات شیمیایی","unit":"کیلوگرم","prod_m":59400,"qty_m":60600,"rate_m":995000,"amount_m":60297,"amount_cum":607434},{"name":"سوسپانسیون","unit":"شیشه","prod_m":null,"qty_m":25070,"rate_m":338373,"amount_m":8483,"amount_cum":70449},{"name":"آمپول","unit":"عدد","prod_m":3022033,"qty_m":3172428,"rate_m":103659,"amount_m":328850,"amount_cum":2244601},{"name":"قطره","unit":"عدد","prod_m":98138,"qty_m":70543,"rate_m":201792,"amount_m":14235,"amount_cum":61408},{"name":"کپسول","unit":"صد عددی","prod_m":83674,"qty_m":79913,"rate_m":1563625,"amount_m":124954,"amount_cum":685146},{"name":"تولید قراردادی","unit":"کیلوگرم","prod_m":null,"qty_m":null,"rate_m":null,"amount_m":0,"amount_cum":0},{"name":"آمپول","unit":"عدد","prod_m":null,"qty_m":null,"rate_m":0,"amount_m":0,"amount_cum":48500},{"name":"قرص و دراژه","unit":"صد عددی","prod_m":null,"qty_m":-7830,"rate_m":490805,"amount_m":-3843,"amount_cum":-140890},{"name":"آمپول","unit":"عدد","prod_m":null,"qty_m":-121940,"rate_m":722,"amount_m":-88,"amount_cum":-5510},{"name":"کپسول","unit":"صد عددی","prod_m":null,"qty_m":-283,"rate_m":1890459,"amount_m":-535,"amount_cum":-6179},{"name":"تخفیفات","unit":null,"prod_m":null,"qty_m":null,"rate_m":null,"amount_m":-115657,"amount_cum":-809701}],"month":1098300,"cum":8132669,"lastYearCum":5617782},{"period":"1404/08/30","publish":"1404/09/06","products":[{"name":"قرص و دراژه","unit":"صد عددی","prod_m":551712,"qty_m":776975,"rate_m":1275158,"amount_m":990766,"amount_cum":6368177},{"name":"محصولات شیمیایی","unit":"کیلوگرم","prod_m":74400,"qty_m":95400,"rate_m":1049392,"amount_m":100112,"amount_cum":707546},{"name":"سوسپانسیون","unit":"شیشه","prod_m":null,"qty_m":28387,"rate_m":338394,"amount_m":9606,"amount_cum":80055},{"name":"آمپول","unit":"عدد","prod_m":2104012,"qty_m":2051557,"rate_m":92768,"amount_m":190318,"amount_cum":2434919},{"name":"قطره","unit":"عدد","prod_m":null,"qty_m":27569,"rate_m":201785,"amount_m":5563,"amount_cum":66971},{"name":"کپسول","unit":"صد عددی","prod_m":29987,"qty_m":71800,"rate_m":1450933,"amount_m":104177,"amount_cum":789323},{"name":"تولید قراردادی","unit":"کیلوگرم","prod_m":null,"qty_m":null,"rate_m":null,"amount_m":0,"amount_cum":0},{"name":"آمپول","unit":"عدد","prod_m":null,"qty_m":null,"rate_m":0,"amount_m":0,"amount_cum":48500},{"name":"قرص و دراژه","unit":"صد عددی","prod_m":null,"qty_m":-662065,"rate_m":28399,"amount_m":-18802,"amount_cum":-159692},{"name":"تخفیفات","unit":null,"prod_m":null,"qty_m":null,"rate_m":null,"amount_m":-175718,"amount_cum":-985419}],"month":1206022,"cum":9338691,"lastYearCum":6182946}],"quarters":[{"period":"1403/09/30","months":12,"audited":false,"consolidated":false,"publish":"1404/01/16","revenue":6925068,"revenue_ly":7709736,"gross":1810203,"gross_ly":2271754,"net":82202,"net_ly":1238199,"eps":143,"eps_ly":2150,"capital":576000,"capital_ly":576000},{"period":"1403/12/30","months":3,"audited":false,"consolidated":false,"publish":"1404/01/30","revenue":1995508,"revenue_ly":2430172,"gross":538787,"gross_ly":621758,"net":105679,"net_ly":356753,"eps":0,"eps_ly":0,"capital":576000,"capital_ly":576000},{"period":"1404/03/31","months":6,"audited":false,"consolidated":false,"publish":"1404/06/16","revenue":3960879,"revenue_ly":4104429,"gross":1295217,"gross_ly":854378,"net":308416,"net_ly":-177203,"eps":535,"eps_ly":-308,"capital":576000,"capital_ly":576000},{"period":"1404/06/31","months":9,"audited":false,"consolidated":false,"publish":"1404/07/30","revenue":7034369,"revenue_ly":5257259,"gross":2143390,"gross_ly":1087093,"net":373063,"net_ly":-461418,"eps":648,"eps_ly":-801,"capital":576000,"capital_ly":576000}]}